demo/demo_custom.py
tufts_moss_wrapper-5.3.2024.dist-info/licenses/LICENSE
tufts_moss_wrapper-5.3.2024.dist-info/METADATA
tufts_moss_wrapper-5.3.2024.dist-info/WHEEL
tufts_moss_wrapper-5.3.2024.dist-info/top_level.txt
tufts_moss_wrapper-5.3.2024.dist-info/RECORD
