Metadata-Version: 2.4
Name: tufts-moss-wrapper
Version: 5.3.2024
Summary: Wrapper over the MOSS submission script that simplifies the interface (optimized for Tufts University's CS department) and cleans up the reporting of results and backs them up for local usage.
Author: Chami Lamelas
License: MIT License
Project-URL: Repository, https://github.com/ChamiLamelas/moss-wrapper
Project-URL: Author, https://sites.google.com/view/chami-lamelas
Requires-Python: >=3.9.2
License-File: LICENSE
Requires-Dist: toml>=0.10.2
Requires-Dist: pytz>=2022.1
Requires-Dist: python-magic>=0.4.24
Dynamic: license-file
